check_pypi_name/__init__.py
check_pypi_name-0.4.0.dist-info/DESCRIPTION.rst
check_pypi_name-0.4.0.dist-info/METADATA
check_pypi_name-0.4.0.dist-info/RECORD
check_pypi_name-0.4.0.dist-info/WHEEL
check_pypi_name-0.4.0.dist-info/metadata.json
check_pypi_name-0.4.0.dist-info/top_level.txt
